{
  "characters": [
    {
      "id": "char_0",
      "name": "Marco",
      "label": "Uninvolved",
      "features": {
        "gender": 0.0,
        "social_status": 0.2,
        "narrative_introduction_timing": 0.0,
        "has_alibi": 0.0,
        "present_at_crime_scene": 0.0,
        "has_motive": 0.0,
        "is_concealing_information": 0.0,
        "has_hidden_relationship": 0.0,
        "motive_type": 0.0,
        "narrative_prominence": 0.8
      }
    },
    {
      "id": "char_1",
      "name": "Zola",
      "label": "Villain",
      "features": {
        "gender": 0.0,
        "social_status": 0.7,
        "narrative_introduction_timing": 0.2,
        "has_alibi": 0.0,
        "present_at_crime_scene": 0.0,
        "has_motive": 0.0,
        "is_concealing_information": 0.0,
        "has_hidden_relationship": 0.0,
        "motive_type": 0.0,
        "narrative_prominence": 0.5
      }
    },
    {
      "id": "char_2",
      "name": "Detective Carl Mørck",
      "label": "Uninvolved",
      "features": {
        "gender": 1.0,
        "social_status": 0.8,
        "narrative_introduction_timing": 0.1,
        "has_alibi": 0.0,
        "present_at_crime_scene": 0.0,
        "has_motive": 0.0,
        "is_concealing_information": 0.0,
        "has_hidden_relationship": 0.0,
        "motive_type": 0.0,
        "narrative_prominence": 0.7
      }
    },
    {
      "id": "char_3",
      "name": "Assad",
      "label": "Uninvolved",
      "features": {
        "gender": 0.0,
        "social_status": 0.6,
        "narrative_introduction_timing": 0.15,
        "has_alibi": 0.0,
        "present_at_crime_scene": 0.0,
        "has_motive": 0.0,
        "is_concealing_information": 0.0,
        "has_hidden_relationship": 1.0,
        "motive_type": 0.0,
        "narrative_prominence": 0.6
      }
    },
    {
      "id": "char_4",
      "name": "Rose",
      "label": "Uninvolved",
      "features": {
        "gender": 1.0,
        "social_status": 0.6,
        "narrative_introduction_timing": 0.25,
        "has_alibi": 0.0,
        "present_at_crime_scene": 0.0,
        "has_motive": 0.0,
        "is_concealing_information": 0.0,
        "has_hidden_relationship": 0.0,
        "motive_type": 0.0,
        "narrative_prominence": 0.4
      }
    },
    {
      "id": "char_5",
      "name": "African man",
      "label": "Victim",
      "features": {
        "gender": 0.0,
        "social_status": 0.3,
        "narrative_introduction_timing": 0.5,
        "has_alibi": 0.0,
        "present_at_crime_scene": 0.0,
        "has_motive": 0.0,
        "is_concealing_information": 0.0,
        "has_hidden_relationship": 0.0,
        "motive_type": 0.0,
        "narrative_prominence": 0.3
      }
    }
  ],
  "edges": [
    {
      "source": "char_0",
      "target": "char_1",
      "weight": 1.0,
      "raw_weight": 4.0
    },
    {
      "source": "char_0",
      "target": "char_3",
      "weight": 0.25,
      "raw_weight": 1.0
    },
    {
      "source": "char_0",
      "target": "char_5",
      "weight": 0.25,
      "raw_weight": 1.0
    },
    {
      "source": "char_1",
      "target": "char_3",
      "weight": 0.25,
      "raw_weight": 1.0
    },
    {
      "source": "char_2",
      "target": "char_3",
      "weight": 0.5,
      "raw_weight": 2.0
    },
    {
      "source": "char_2",
      "target": "char_4",
      "weight": 0.5,
      "raw_weight": 2.0
    },
    {
      "source": "char_2",
      "target": "char_5",
      "weight": 0.25,
      "raw_weight": 1.0
    },
    {
      "source": "char_3",
      "target": "char_4",
      "weight": 0.25,
      "raw_weight": 1.0
    },
    {
      "source": "char_3",
      "target": "char_5",
      "weight": 0.25,
      "raw_weight": 1.0
    }
  ],
  "metadata": {
    "entry_id": "NOV_379",
    "title": "The Marco Effect",
    "author": "Jussi Adler-Olsen",
    "year": 2012,
    "medium": "Novel"
  },
  "graph_stats": {
    "num_characters": 6,
    "num_edges": 9,
    "max_raw_weight": 4.0
  }
}