{
  "characters": [
    {
      "id": "char_0",
      "name": "Sherlock Holmes",
      "label": "Uninvolved",
      "features": {
        "gender": 0.0,
        "social_status": 1.0,
        "narrative_introduction_timing": 0.0,
        "has_alibi": 0.0,
        "present_at_crime_scene": 1.0,
        "has_motive": 0.0,
        "is_concealing_information": 0.0,
        "has_hidden_relationship": 0.0,
        "motive_type": 0.0,
        "narrative_prominence": 1.0
      }
    },
    {
      "id": "char_1",
      "name": "Dr. John Watson",
      "label": "Uninvolved",
      "features": {
        "gender": 0.0,
        "social_status": 0.75,
        "narrative_introduction_timing": 0.0,
        "has_alibi": 0.0,
        "present_at_crime_scene": 1.0,
        "has_motive": 0.0,
        "is_concealing_information": 0.0,
        "has_hidden_relationship": 0.0,
        "motive_type": 0.0,
        "narrative_prominence": 0.5
      }
    },
    {
      "id": "char_2",
      "name": "Helen Stoner",
      "label": "Victim",
      "features": {
        "gender": 1.0,
        "social_status": 0.5,
        "narrative_introduction_timing": 0.25,
        "has_alibi": 0.0,
        "present_at_crime_scene": 0.0,
        "has_motive": 0.0,
        "is_concealing_information": 0.0,
        "has_hidden_relationship": 0.0,
        "motive_type": 0.0,
        "narrative_prominence": 0.5
      }
    },
    {
      "id": "char_3",
      "name": "Julia Stoner",
      "label": "Victim",
      "features": {
        "gender": 1.0,
        "social_status": 0.5,
        "narrative_introduction_timing": 0.25,
        "has_alibi": 0.0,
        "present_at_crime_scene": 0.0,
        "has_motive": 0.0,
        "is_concealing_information": 0.0,
        "has_hidden_relationship": 0.0,
        "motive_type": 0.0,
        "narrative_prominence": 0.5
      }
    },
    {
      "id": "char_4",
      "name": "Dr. Grimesby Roylott",
      "label": "Villain",
      "features": {
        "gender": 0.0,
        "social_status": 0.75,
        "narrative_introduction_timing": 0.125,
        "has_alibi": 0.0,
        "present_at_crime_scene": 1.0,
        "has_motive": 1.0,
        "is_concealing_information": 0.0,
        "has_hidden_relationship": 0.0,
        "motive_type": 0.66,
        "narrative_prominence": 0.75
      }
    },
    {
      "id": "char_5",
      "name": "Helen's mother",
      "label": "Victim",
      "features": {
        "gender": 1.0,
        "social_status": 0.75,
        "narrative_introduction_timing": 0.0,
        "has_alibi": 0.0,
        "present_at_crime_scene": 0.0,
        "has_motive": 0.0,
        "is_concealing_information": 0.0,
        "has_hidden_relationship": 0.0,
        "motive_type": 0.0,
        "narrative_prominence": 0.25
      }
    },
    {
      "id": "char_6",
      "name": "Indian butler",
      "label": "Uninvolved",
      "features": {
        "gender": 0.0,
        "social_status": 0.25,
        "narrative_introduction_timing": 0.0,
        "has_alibi": 0.0,
        "present_at_crime_scene": 0.0,
        "has_motive": 0.0,
        "is_concealing_information": 0.0,
        "has_hidden_relationship": 0.0,
        "motive_type": 0.0,
        "narrative_prominence": 0.25
      }
    }
  ],
  "edges": [
    {
      "source": "char_0",
      "target": "char_1",
      "weight": 0.25,
      "raw_weight": 1.0
    },
    {
      "source": "char_0",
      "target": "char_2",
      "weight": 0.25,
      "raw_weight": 1.0
    },
    {
      "source": "char_0",
      "target": "char_4",
      "weight": 1.0,
      "raw_weight": 4.0
    },
    {
      "source": "char_2",
      "target": "char_3",
      "weight": 0.25,
      "raw_weight": 1.0
    },
    {
      "source": "char_2",
      "target": "char_4",
      "weight": 0.5,
      "raw_weight": 2.0
    },
    {
      "source": "char_3",
      "target": "char_4",
      "weight": 0.5,
      "raw_weight": 2.0
    },
    {
      "source": "char_4",
      "target": "char_5",
      "weight": 0.25,
      "raw_weight": 1.0
    },
    {
      "source": "char_4",
      "target": "char_6",
      "weight": 0.25,
      "raw_weight": 1.0
    }
  ],
  "metadata": {
    "entry_id": "SHO_002",
    "title": "The Adventure of the Speckled Band",
    "author": "Arthur Conan Doyle",
    "year": 1892,
    "medium": "Short Story"
  },
  "graph_stats": {
    "num_characters": 7,
    "num_edges": 8,
    "max_raw_weight": 4.0
  }
}