{
  "characters": [
    {
      "id": "char_0",
      "name": "DCI Cassie Stuart",
      "label": "Uninvolved",
      "features": {
        "gender": 1.0,
        "social_status": 0.7,
        "narrative_introduction_timing": 0.0,
        "has_alibi": 0.0,
        "present_at_crime_scene": 0.0,
        "has_motive": 0.0,
        "is_concealing_information": 0.0,
        "has_hidden_relationship": 0.0,
        "motive_type": 0.0,
        "narrative_prominence": 1.0
      }
    },
    {
      "id": "char_1",
      "name": "DS Sunny Khan",
      "label": "Uninvolved",
      "features": {
        "gender": 0.0,
        "social_status": 0.7,
        "narrative_introduction_timing": 0.2,
        "has_alibi": 0.0,
        "present_at_crime_scene": 0.0,
        "has_motive": 0.0,
        "is_concealing_information": 0.0,
        "has_hidden_relationship": 0.0,
        "motive_type": 0.0,
        "narrative_prominence": 0.8
      }
    },
    {
      "id": "char_2",
      "name": "David Walker",
      "label": "Victim",
      "features": {
        "gender": 1.0,
        "social_status": 0.3,
        "narrative_introduction_timing": 0.5,
        "has_alibi": 0.0,
        "present_at_crime_scene": 0.0,
        "has_motive": 0.0,
        "is_concealing_information": 0.0,
        "has_hidden_relationship": 0.0,
        "motive_type": 0.0,
        "narrative_prominence": 0.6
      }
    },
    {
      "id": "char_3",
      "name": "Marion Kelsey",
      "label": "Uninvolved",
      "features": {
        "gender": 1.0,
        "social_status": 0.5,
        "narrative_introduction_timing": 0.3,
        "has_alibi": 0.0,
        "present_at_crime_scene": 0.0,
        "has_motive": 0.0,
        "is_concealing_information": 0.0,
        "has_hidden_relationship": 0.0,
        "motive_type": 0.0,
        "narrative_prominence": 0.5
      }
    },
    {
      "id": "char_4",
      "name": "Colin Osborne",
      "label": "Uninvolved",
      "features": {
        "gender": 0.0,
        "social_status": 0.8,
        "narrative_introduction_timing": 0.4,
        "has_alibi": 0.0,
        "present_at_crime_scene": 0.0,
        "has_motive": 0.0,
        "is_concealing_information": 0.0,
        "has_hidden_relationship": 0.0,
        "motive_type": 0.0,
        "narrative_prominence": 0.5
      }
    },
    {
      "id": "char_5",
      "name": "Elise Penning",
      "label": "Uninvolved",
      "features": {
        "gender": 1.0,
        "social_status": 0.6,
        "narrative_introduction_timing": 0.7,
        "has_alibi": 0.0,
        "present_at_crime_scene": 0.0,
        "has_motive": 0.0,
        "is_concealing_information": 0.0,
        "has_hidden_relationship": 0.0,
        "motive_type": 0.0,
        "narrative_prominence": 0.5
      }
    },
    {
      "id": "char_6",
      "name": "Tony Wetherall",
      "label": "Uninvolved",
      "features": {
        "gender": 0.0,
        "social_status": 0.9,
        "narrative_introduction_timing": 0.8,
        "has_alibi": 0.0,
        "present_at_crime_scene": 0.0,
        "has_motive": 0.0,
        "is_concealing_information": 0.0,
        "has_hidden_relationship": 0.0,
        "motive_type": 0.0,
        "narrative_prominence": 0.5
      }
    },
    {
      "id": "char_7",
      "name": "Ray Dawson",
      "label": "Villain",
      "features": {
        "gender": 0.0,
        "social_status": 0.4,
        "narrative_introduction_timing": 0.0,
        "has_alibi": 0.0,
        "present_at_crime_scene": 0.0,
        "has_motive": 0.0,
        "is_concealing_information": 0.0,
        "has_hidden_relationship": 0.0,
        "motive_type": 0.0,
        "narrative_prominence": 0.3
      }
    }
  ],
  "edges": [
    {
      "source": "char_0",
      "target": "char_1",
      "weight": 1.0,
      "raw_weight": 1.0
    },
    {
      "source": "char_0",
      "target": "char_2",
      "weight": 1.0,
      "raw_weight": 1.0
    },
    {
      "source": "char_0",
      "target": "char_3",
      "weight": 1.0,
      "raw_weight": 1.0
    },
    {
      "source": "char_0",
      "target": "char_4",
      "weight": 1.0,
      "raw_weight": 1.0
    },
    {
      "source": "char_0",
      "target": "char_5",
      "weight": 1.0,
      "raw_weight": 1.0
    },
    {
      "source": "char_0",
      "target": "char_6",
      "weight": 1.0,
      "raw_weight": 1.0
    },
    {
      "source": "char_1",
      "target": "char_2",
      "weight": 1.0,
      "raw_weight": 1.0
    },
    {
      "source": "char_2",
      "target": "char_7",
      "weight": 1.0,
      "raw_weight": 1.0
    },
    {
      "source": "char_3",
      "target": "char_4",
      "weight": 1.0,
      "raw_weight": 1.0
    },
    {
      "source": "char_3",
      "target": "char_7",
      "weight": 1.0,
      "raw_weight": 1.0
    },
    {
      "source": "char_4",
      "target": "char_5",
      "weight": 1.0,
      "raw_weight": 1.0
    },
    {
      "source": "char_4",
      "target": "char_7",
      "weight": 1.0,
      "raw_weight": 1.0
    },
    {
      "source": "char_5",
      "target": "char_7",
      "weight": 1.0,
      "raw_weight": 1.0
    },
    {
      "source": "char_6",
      "target": "char_7",
      "weight": 1.0,
      "raw_weight": 1.0
    }
  ],
  "metadata": {
    "entry_id": "TVE_130",
    "title": "Unforgotten: Series 2",
    "author": "Andy Wilson",
    "year": 2017,
    "medium": "TV Episode"
  },
  "graph_stats": {
    "num_characters": 8,
    "num_edges": 14,
    "max_raw_weight": 1.0
  }
}