{
  "characters": [
    {
      "id": "char_0",
      "name": "Jane Wilkinson",
      "label": "Uninvolved",
      "features": {
        "gender": 1,
        "social_status": 1,
        "narrative_introduction_timing": 0.0,
        "has_alibi": 1,
        "present_at_crime_scene": -1,
        "has_motive": -1,
        "is_concealing_information": -1,
        "has_hidden_relationship": -1,
        "motive_type": -1,
        "narrative_prominence": 1
      }
    },
    {
      "id": "char_1",
      "name": "Lord Edgware",
      "label": "Victim",
      "features": {
        "gender": 0,
        "social_status": 1,
        "narrative_introduction_timing": 0.25,
        "has_alibi": -1,
        "present_at_crime_scene": 1,
        "has_motive": -1,
        "is_concealing_information": -1,
        "has_hidden_relationship": -1,
        "motive_type": -1,
        "narrative_prominence": 0.5
      }
    },
    {
      "id": "char_2",
      "name": "Captain Hastings",
      "label": "Uninvolved",
      "features": {
        "gender": 0,
        "social_status": 0.5,
        "narrative_introduction_timing": 0.125,
        "has_alibi": -1,
        "present_at_crime_scene": -1,
        "has_motive": -1,
        "is_concealing_information": -1,
        "has_hidden_relationship": -1,
        "motive_type": -1,
        "narrative_prominence": 0.5
      }
    },
    {
      "id": "char_3",
      "name": "Chief Inspector Japp",
      "label": "Uninvolved",
      "features": {
        "gender": 0,
        "social_status": 0.5,
        "narrative_introduction_timing": 0.125,
        "has_alibi": -1,
        "present_at_crime_scene": -1,
        "has_motive": -1,
        "is_concealing_information": -1,
        "has_hidden_relationship": -1,
        "motive_type": -1,
        "narrative_prominence": 0.5
      }
    },
    {
      "id": "char_4",
      "name": "Miss Lemon",
      "label": "Uninvolved",
      "features": {
        "gender": 1,
        "social_status": 0.5,
        "narrative_introduction_timing": 0.125,
        "has_alibi": -1,
        "present_at_crime_scene": -1,
        "has_motive": -1,
        "is_concealing_information": -1,
        "has_hidden_relationship": -1,
        "motive_type": -1,
        "narrative_prominence": 0.5
      }
    },
    {
      "id": "char_5",
      "name": "Duke of Merton",
      "label": "Uninvolved",
      "features": {
        "gender": 0,
        "social_status": 1,
        "narrative_introduction_timing": 0.5,
        "has_alibi": -1,
        "present_at_crime_scene": -1,
        "has_motive": -1,
        "is_concealing_information": -1,
        "has_hidden_relationship": -1,
        "motive_type": -1,
        "narrative_prominence": 0.5
      }
    },
    {
      "id": "char_6",
      "name": "Lord Edgware's butler",
      "label": "Witness",
      "features": {
        "gender": 0,
        "social_status": 0.5,
        "narrative_introduction_timing": 0.375,
        "has_alibi": -1,
        "present_at_crime_scene": -1,
        "has_motive": -1,
        "is_concealing_information": -1,
        "has_hidden_relationship": -1,
        "motive_type": -1,
        "narrative_prominence": 0.5
      }
    },
    {
      "id": "char_7",
      "name": "Ronald Marsh",
      "label": "Villain",
      "features": {
        "gender": 0,
        "social_status": 0.5,
        "narrative_introduction_timing": 0.75,
        "has_alibi": -1,
        "present_at_crime_scene": -1,
        "has_motive": 1,
        "is_concealing_information": 1,
        "has_hidden_relationship": -1,
        "motive_type": "money",
        "narrative_prominence": 0.5
      }
    },
    {
      "id": "char_8",
      "name": "Carlotta Adams",
      "label": "Victim",
      "features": {
        "gender": 1,
        "social_status": 0.5,
        "narrative_introduction_timing": 0.625,
        "has_alibi": -1,
        "present_at_crime_scene": -1,
        "has_motive": -1,
        "is_concealing_information": -1,
        "has_hidden_relationship": -1,
        "motive_type": -1,
        "narrative_prominence": 0.5
      }
    }
  ],
  "occupations": [
    {
      "id": "occ_0",
      "name": "Actor/Actress",
      "features": {
        "authority_level": 0.5,
        "access_level": 1,
        "capability_level": 0.5
      }
    },
    {
      "id": "occ_1",
      "name": "Butler",
      "features": {
        "authority_level": 0.2,
        "access_level": 0.8,
        "capability_level": 0.5
      }
    },
    {
      "id": "occ_2",
      "name": "Detective",
      "features": {
        "authority_level": 1,
        "access_level": 0.8,
        "capability_level": 0.9
      }
    },
    {
      "id": "occ_3",
      "name": "Heir/Nephew",
      "features": {
        "authority_level": 0.5,
        "access_level": 0.8,
        "capability_level": 0.7
      }
    },
    {
      "id": "occ_4",
      "name": "Impressionist",
      "features": {
        "authority_level": 0.5,
        "access_level": 1,
        "capability_level": 0.9
      }
    }
  ],
  "locations": [
    {
      "id": "loc_0",
      "name": "Lord Edgware's London house",
      "features": {
        "accessibility": 0.5,
        "isolability": 0.3,
        "evidentiary_value": 1
      }
    },
    {
      "id": "loc_1",
      "name": "Dinner party location",
      "features": {
        "accessibility": 0.5,
        "isolability": 0.7,
        "evidentiary_value": 0.8
      }
    },
    {
      "id": "loc_2",
      "name": "Paris (related to Carlotta Adams)",
      "features": {
        "accessibility": 1,
        "isolability": 0.5,
        "evidentiary_value": 0.5
      }
    }
  ],
  "organizations": [],
  "edges": [
    {
      "source": "char_0",
      "target": "char_1",
      "relation": "married to",
      "directed": true
    },
    {
      "source": "char_1",
      "target": "char_0",
      "relation": "married to",
      "directed": true
    },
    {
      "source": "char_0",
      "target": "occ_0",
      "relation": "employed as",
      "directed": true
    },
    {
      "source": "char_5",
      "target": "char_0",
      "relation": "romantically involved with",
      "directed": true
    },
    {
      "source": "char_1",
      "target": "char_6",
      "relation": "employs",
      "directed": true
    },
    {
      "source": "char_0",
      "target": "char_1",
      "relation": "wants to divorce",
      "directed": true
    },
    {
      "source": "char_0",
      "target": "char_2",
      "relation": "friends with",
      "directed": true
    },
    {
      "source": "char_0",
      "target": "char_3",
      "relation": "friends with",
      "directed": true
    },
    {
      "source": "char_1",
      "target": "char_7",
      "relation": "related to",
      "directed": true
    },
    {
      "source": "char_7",
      "target": "char_1",
      "relation": "related to",
      "directed": true
    },
    {
      "source": "char_7",
      "target": "char_0",
      "relation": "romantically involved with",
      "directed": true
    },
    {
      "source": "char_8",
      "target": "occ_4",
      "relation": "employed as",
      "directed": true
    },
    {
      "source": "char_8",
      "target": "char_0",
      "relation": "impersonates",
      "directed": true
    },
    {
      "source": "char_1",
      "target": "loc_0",
      "relation": "owns",
      "directed": true
    },
    {
      "source": "char_6",
      "target": "char_8",
      "relation": "mistakes for",
      "directed": true
    },
    {
      "source": "char_7",
      "target": "char_1",
      "relation": "kills",
      "directed": true
    },
    {
      "source": "char_8",
      "target": "loc_2",
      "relation": "present at",
      "directed": true
    },
    {
      "source": "char_7",
      "target": "char_8",
      "relation": "kills",
      "directed": true
    },
    {
      "source": "char_7",
      "target": "loc_0",
      "relation": "present at",
      "directed": true
    },
    {
      "source": "char_3",
      "target": "char_1",
      "relation": "investigates",
      "directed": true
    },
    {
      "source": "char_2",
      "target": "char_1",
      "relation": "investigates",
      "directed": true
    },
    {
      "source": "char_0",
      "target": "char_7",
      "relation": "accuses",
      "directed": true
    },
    {
      "source": "char_7",
      "target": "char_0",
      "relation": "deceives",
      "directed": true
    },
    {
      "source": "char_7",
      "target": "char_3",
      "relation": "hides behind",
      "directed": true
    },
    {
      "source": "char_8",
      "target": "char_7",
      "relation": "hired by",
      "directed": true
    }
  ],
  "metadata": {
    "entry_id": "TVE_039",
    "title": "Poirot: Lord Edgware Dies",
    "author": "Brian Farnham",
    "year": 2000,
    "medium": "TV Episode"
  }
}