{
  "characters": [
    {
      "id": "char_0",
      "name": "Richard Papen",
      "label": "Uninvolved",
      "features": {
        "gender": 0,
        "social_status": 0.5,
        "narrative_introduction_timing": 0.0,
        "has_alibi": 1,
        "present_at_crime_scene": 0,
        "has_motive": 0,
        "is_concealing_information": 1,
        "has_hidden_relationship": 0,
        "motive_type": -1,
        "narrative_prominence": 1
      }
    },
    {
      "id": "char_1",
      "name": "Julian Morrow",
      "label": "Uninvolved",
      "features": {
        "gender": 0,
        "social_status": 1,
        "narrative_introduction_timing": 0.2,
        "has_alibi": 1,
        "present_at_crime_scene": 0,
        "has_motive": 0,
        "is_concealing_information": 1,
        "has_hidden_relationship": 0,
        "motive_type": -1,
        "narrative_prominence": 0.5
      }
    },
    {
      "id": "char_2",
      "name": "Charles Macaulay",
      "label": "Villain",
      "features": {
        "gender": 0,
        "social_status": 0.5,
        "narrative_introduction_timing": 0.2,
        "has_alibi": 0,
        "present_at_crime_scene": 1,
        "has_motive": 1,
        "is_concealing_information": 1,
        "has_hidden_relationship": 1,
        "motive_type": 0.33,
        "narrative_prominence": 0.5
      }
    },
    {
      "id": "char_3",
      "name": "Camilla Macaulay",
      "label": "Victim",
      "features": {
        "gender": 1,
        "social_status": 0.5,
        "narrative_introduction_timing": 0.2,
        "has_alibi": 1,
        "present_at_crime_scene": 0,
        "has_motive": 0,
        "is_concealing_information": 0,
        "has_hidden_relationship": 1,
        "motive_type": -1,
        "narrative_prominence": 0.5
      }
    },
    {
      "id": "char_4",
      "name": "Francis Abernathy",
      "label": "Villain",
      "features": {
        "gender": 0,
        "social_status": 0.5,
        "narrative_introduction_timing": 0.2,
        "has_alibi": 1,
        "present_at_crime_scene": 0,
        "has_motive": 1,
        "is_concealing_information": 1,
        "has_hidden_relationship": 1,
        "motive_type": 0.33,
        "narrative_prominence": 0.5
      }
    },
    {
      "id": "char_5",
      "name": "Henry Winter",
      "label": "Villain",
      "features": {
        "gender": 0,
        "social_status": 0.5,
        "narrative_introduction_timing": 0.2,
        "has_alibi": 1,
        "present_at_crime_scene": 0,
        "has_motive": 1,
        "is_concealing_information": 1,
        "has_hidden_relationship": 1,
        "motive_type": 0.33,
        "narrative_prominence": 0.5
      }
    },
    {
      "id": "char_6",
      "name": "Edmund 'Bunny' Corcoran",
      "label": "Victim",
      "features": {
        "gender": 0,
        "social_status": 0.5,
        "narrative_introduction_timing": 0.2,
        "has_alibi": 0,
        "present_at_crime_scene": 1,
        "has_motive": 0,
        "is_concealing_information": 0,
        "has_hidden_relationship": 0,
        "motive_type": -1,
        "narrative_prominence": 0.5
      }
    }
  ],
  "occupations": [
    {
      "id": "occ_0",
      "name": "Literature student",
      "features": {
        "authority_level": 0.2,
        "access_level": 0.5,
        "capability_level": 0.3
      }
    },
    {
      "id": "occ_1",
      "name": "Classics professor",
      "features": {
        "authority_level": 0.9,
        "access_level": 0.5,
        "capability_level": 0.7
      }
    }
  ],
  "locations": [
    {
      "id": "loc_0",
      "name": "Plano, California",
      "features": {
        "accessibility": 1,
        "isolability": 0.2,
        "evidentiary_value": 0.5
      }
    },
    {
      "id": "loc_1",
      "name": "Hampden College, Vermont",
      "features": {
        "accessibility": 0.8,
        "isolability": 0.4,
        "evidentiary_value": 0.7
      }
    },
    {
      "id": "loc_2",
      "name": "Francis's country estate",
      "features": {
        "accessibility": 0.3,
        "isolability": 0.8,
        "evidentiary_value": 1
      }
    },
    {
      "id": "loc_3",
      "name": "Rome, Italy",
      "features": {
        "accessibility": 0.5,
        "isolability": 0.6,
        "evidentiary_value": 0.5
      }
    },
    {
      "id": "loc_4",
      "name": "Unheated warehouse",
      "features": {
        "accessibility": 0.1,
        "isolability": 0.9,
        "evidentiary_value": 0.5
      }
    },
    {
      "id": "loc_5",
      "name": "Hotel room",
      "features": {
        "accessibility": 0.7,
        "isolability": 0.3,
        "evidentiary_value": 1
      }
    }
  ],
  "organizations": [
    {
      "id": "org_0",
      "name": "Hampden College",
      "features": {
        "institutional_power": 0.8,
        "secrecy_level": 0.3,
        "financial_scale": 0.5
      }
    }
  ],
  "edges": [
    {
      "source": "char_0",
      "target": "occ_0",
      "relation": "employed as",
      "directed": true
    },
    {
      "source": "char_1",
      "target": "occ_1",
      "relation": "leads",
      "directed": true
    },
    {
      "source": "char_0",
      "target": "loc_1",
      "relation": "resides at",
      "directed": true
    },
    {
      "source": "char_2",
      "target": "char_3",
      "relation": "related to",
      "directed": true
    },
    {
      "source": "char_2",
      "target": "char_3",
      "relation": "friends with",
      "directed": true
    },
    {
      "source": "char_0",
      "target": "char_4",
      "relation": "friends with",
      "directed": true
    },
    {
      "source": "char_5",
      "target": "char_4",
      "relation": "friends with",
      "directed": true
    },
    {
      "source": "char_6",
      "target": "char_4",
      "relation": "friends with",
      "directed": true
    },
    {
      "source": "char_0",
      "target": "char_5",
      "relation": "friends with",
      "directed": true
    },
    {
      "source": "char_1",
      "target": "char_2",
      "relation": "employs",
      "directed": true
    },
    {
      "source": "char_1",
      "target": "char_3",
      "relation": "employs",
      "directed": true
    },
    {
      "source": "char_1",
      "target": "char_4",
      "relation": "employs",
      "directed": true
    },
    {
      "source": "char_1",
      "target": "char_5",
      "relation": "employs",
      "directed": true
    },
    {
      "source": "char_1",
      "target": "char_6",
      "relation": "employs",
      "directed": true
    },
    {
      "source": "char_2",
      "target": "char_6",
      "relation": "blackmails",
      "directed": true
    },
    {
      "source": "char_4",
      "target": "char_6",
      "relation": "gives money to",
      "directed": true
    },
    {
      "source": "char_5",
      "target": "char_6",
      "relation": "kills",
      "directed": true
    },
    {
      "source": "char_2",
      "target": "loc_2",
      "relation": "owns",
      "directed": true
    },
    {
      "source": "char_4",
      "target": "char_5",
      "relation": "lives with",
      "directed": true
    },
    {
      "source": "char_0",
      "target": "loc_3",
      "relation": "present at",
      "directed": true
    },
    {
      "source": "char_5",
      "target": "char_0",
      "relation": "rescues",
      "directed": true
    },
    {
      "source": "char_5",
      "target": "loc_4",
      "relation": "owns",
      "directed": true
    },
    {
      "source": "char_2",
      "target": "char_6",
      "relation": "discovers",
      "directed": true
    },
    {
      "source": "char_2",
      "target": "char_5",
      "relation": "conflicts with",
      "directed": true
    },
    {
      "source": "char_4",
      "target": "char_6",
      "relation": "witnessed by",
      "directed": true
    },
    {
      "source": "char_5",
      "target": "char_6",
      "relation": "deceives",
      "directed": true
    },
    {
      "source": "char_4",
      "target": "char_2",
      "relation": "protects",
      "directed": true
    },
    {
      "source": "char_3",
      "target": "char_2",
      "relation": "romantically involved with",
      "directed": true
    },
    {
      "source": "char_5",
      "target": "char_3",
      "relation": "romantically involved with",
      "directed": true
    },
    {
      "source": "char_4",
      "target": "char_2",
      "relation": "business partner of",
      "directed": true
    },
    {
      "source": "char_5",
      "target": "char_2",
      "relation": "business partner of",
      "directed": true
    },
    {
      "source": "char_6",
      "target": "loc_3",
      "relation": "present at",
      "directed": true
    },
    {
      "source": "char_6",
      "target": "loc_4",
      "relation": "resides at",
      "directed": true
    },
    {
      "source": "char_0",
      "target": "char_2",
      "relation": "suspects",
      "directed": true
    },
    {
      "source": "char_0",
      "target": "char_3",
      "relation": "suspects",
      "directed": true
    },
    {
      "source": "char_0",
      "target": "char_4",
      "relation": "suspects",
      "directed": true
    },
    {
      "source": "char_0",
      "target": "char_5",
      "relation": "suspects",
      "directed": true
    },
    {
      "source": "char_0",
      "target": "char_6",
      "relation": "suspects",
      "directed": true
    },
    {
      "source": "char_1",
      "target": "char_2",
      "relation": "suspects",
      "directed": true
    },
    {
      "source": "char_1",
      "target": "char_3",
      "relation": "suspects",
      "directed": true
    },
    {
      "source": "char_1",
      "target": "char_4",
      "relation": "suspects",
      "directed": true
    },
    {
      "source": "char_1",
      "target": "char_5",
      "relation": "suspects",
      "directed": true
    },
    {
      "source": "char_1",
      "target": "char_6",
      "relation": "suspects",
      "directed": true
    },
    {
      "source": "char_2",
      "target": "char_5",
      "relation": "conflicts with",
      "directed": true
    },
    {
      "source": "char_3",
      "target": "char_2",
      "relation": "accuses",
      "directed": true
    },
    {
      "source": "char_4",
      "target": "char_6",
      "relation": "hires",
      "directed": true
    },
    {
      "source": "char_5",
      "target": "char_6",
      "relation": "hires",
      "directed": true
    },
    {
      "source": "char_2",
      "target": "char_4",
      "relation": "works with",
      "directed": true
    },
    {
      "source": "char_3",
      "target": "char_5",
      "relation": "works with",
      "directed": true
    },
    {
      "source": "char_6",
      "target": "loc_1",
      "relation": "near to",
      "directed": true
    },
    {
      "source": "char_0",
      "target": "org_0",
      "relation": "affiliated with",
      "directed": true
    },
    {
      "source": "char_2",
      "target": "org_0",
      "relation": "affiliated with",
      "directed": true
    },
    {
      "source": "char_3",
      "target": "org_0",
      "relation": "affiliated with",
      "directed": true
    },
    {
      "source": "char_4",
      "target": "org_0",
      "relation": "affiliated with",
      "directed": true
    },
    {
      "source": "char_5",
      "target": "org_0",
      "relation": "affiliated with",
      "directed": true
    },
    {
      "source": "char_6",
      "target": "org_0",
      "relation": "affiliated with",
      "directed": true
    },
    {
      "source": "char_2",
      "target": "loc_5",
      "relation": "resides at",
      "directed": true
    },
    {
      "source": "char_4",
      "target": "loc_5",
      "relation": "lives with",
      "directed": true
    },
    {
      "source": "char_0",
      "target": "char_6",
      "relation": "investigates",
      "directed": true
    },
    {
      "source": "char_1",
      "target": "char_6",
      "relation": "investigates",
      "directed": true
    },
    {
      "source": "char_5",
      "target": "char_2",
      "relation": "deceives",
      "directed": true
    },
    {
      "source": "char_4",
      "target": "char_6",
      "relation": "gives money to",
      "directed": true
    },
    {
      "source": "char_5",
      "target": "char_6",
      "relation": "gives money to",
      "directed": true
    },
    {
      "source": "char_2",
      "target": "char_6",
      "relation": "blackmails",
      "directed": true
    },
    {
      "source": "char_5",
      "target": "char_6",
      "relation": "kills",
      "directed": true
    },
    {
      "source": "char_0",
      "target": "char_2",
      "relation": "discovers",
      "directed": true
    },
    {
      "source": "char_0",
      "target": "char_3",
      "relation": "discovers",
      "directed": true
    },
    {
      "source": "char_0",
      "target": "char_4",
      "relation": "discovers",
      "directed": true
    },
    {
      "source": "char_0",
      "target": "char_5",
      "relation": "discovers",
      "directed": true
    },
    {
      "source": "char_1",
      "target": "char_2",
      "relation": "discovers",
      "directed": true
    },
    {
      "source": "char_1",
      "target": "char_3",
      "relation": "discovers",
      "directed": true
    },
    {
      "source": "char_1",
      "target": "char_4",
      "relation": "discovers",
      "directed": true
    },
    {
      "source": "char_1",
      "target": "char_5",
      "relation": "discovers",
      "directed": true
    },
    {
      "source": "char_2",
      "target": "char_3",
      "relation": "deceives",
      "directed": true
    },
    {
      "source": "char_4",
      "target": "char_6",
      "relation": "deceives",
      "directed": true
    },
    {
      "source": "char_5",
      "target": "char_6",
      "relation": "deceives",
      "directed": true
    },
    {
      "source": "char_2",
      "target": "char_5",
      "relation": "protects",
      "directed": true
    },
    {
      "source": "char_3",
      "target": "char_2",
      "relation": "romantically involved with",
      "directed": true
    },
    {
      "source": "char_5",
      "target": "char_3",
      "relation": "romantically involved with",
      "directed": true
    },
    {
      "source": "char_4",
      "target": "char_2",
      "relation": "business partner of",
      "directed": true
    },
    {
      "source": "char_5",
      "target": "char_2",
      "relation": "business partner of",
      "directed": true
    },
    {
      "source": "char_6",
      "target": "loc_1",
      "relation": "near to",
      "directed": true
    },
    {
      "source": "char_0",
      "target": "char_5",
      "relation": "suspects",
      "directed": true
    },
    {
      "source": "char_1",
      "target": "char_5",
      "relation": "suspects",
      "directed": true
    },
    {
      "source": "char_2",
      "target": "char_5",
      "relation": "conflicts with",
      "directed": true
    },
    {
      "source": "char_3",
      "target": "char_5",
      "relation": "accuses",
      "directed": true
    },
    {
      "source": "char_4",
      "target": "char_5",
      "relation": "hires",
      "directed": true
    },
    {
      "source": "char_5",
      "target": "char_2",
      "relation": "works with",
      "directed": true
    },
    {
      "source": "char_6",
      "target": "char_3",
      "relation": "works with",
      "directed": true
    },
    {
      "source": "loc_1",
      "target": "loc_5",
      "relation": "near to",
      "directed": false
    },
    {
      "source": "org_0",
      "target": "loc_1",
      "relation": "located at",
      "directed": true
    },
    {
      "source": "char_0",
      "target": "char_2",
      "relation": "accuses",
      "directed": true
    },
    {
      "source": "char_0",
      "target": "char_3",
      "relation": "accuses",
      "directed": true
    },
    {
      "source": "char_0",
      "target": "char_4",
      "relation": "accuses",
      "directed": true
    },
    {
      "source": "char_0",
      "target": "char_5",
      "relation": "accuses",
      "directed": true
    },
    {
      "source": "char_1",
      "target": "char_2",
      "relation": "accuses",
      "directed": true
    },
    {
      "source": "char_1",
      "target": "char_3",
      "relation": "accuses",
      "directed": true
    },
    {
      "source": "char_1",
      "target": "char_4",
      "relation": "accuses",
      "directed": true
    },
    {
      "source": "char_1",
      "target": "char_5",
      "relation": "accuses",
      "directed": true
    },
    {
      "source": "char_2",
      "target": "char_3",
      "relation": "investigates",
      "directed": true
    },
    {
      "source": "char_4",
      "target": "char_6",
      "relation": "investigates",
      "directed": true
    },
    {
      "source": "char_5",
      "target": "char_6",
      "relation": "investigates",
      "directed": true
    },
    {
      "source": "char_2",
      "target": "char_5",
      "relation": "deceives",
      "directed": true
    },
    {
      "source": "char_3",
      "target": "char_2",
      "relation": "works with",
      "directed": true
    },
    {
      "source": "char_5",
      "target": "char_3",
      "relation": "works with",
      "directed": true
    },
    {
      "source": "char_6",
      "target": "loc_2",
      "relation": "near to",
      "directed": true
    },
    {
      "source": "char_0",
      "target": "char_1",
      "relation": "discovers",
      "directed": true
    },
    {
      "source": "char_2",
      "target": "char_3",
      "relation": "deceives",
      "directed": true
    },
    {
      "source": "char_4",
      "target": "char_6",
      "relation": "deceives",
      "directed": true
    },
    {
      "source": "char_5",
      "target": "char_6",
      "relation": "deceives",
      "directed": true
    },
    {
      "source": "char_2",
      "target": "char_5",
      "relation": "protects",
      "directed": true
    },
    {
      "source": "char_3",
      "target": "char_2",
      "relation": "romantically involved with",
      "directed": true
    },
    {
      "source": "char_5",
      "target": "char_3",
      "relation": "romantically involved with",
      "directed": true
    },
    {
      "source": "char_4",
      "target": "char_2",
      "relation": "business partner of",
      "directed": true
    },
    {
      "source": "char_5",
      "target": "char_2",
      "relation": "business partner of",
      "directed": true
    },
    {
      "source": "char_6",
      "target": "loc_1",
      "relation": "near to",
      "directed": true
    },
    {
      "source": "char_0",
      "target": "char_6",
      "relation": "investigates",
      "directed": true
    },
    {
      "source": "char_1",
      "target": "char_6",
      "relation": "investigates",
      "directed": true
    },
    {
      "source": "char_5",
      "target": "char_6",
      "relation": "kills",
      "directed": true
    },
    {
      "source": "char_0",
      "target": "char_2",
      "relation": "suspects",
      "directed": true
    },
    {
      "source": "char_0",
      "target": "char_3",
      "relation": "suspects",
      "directed": true
    },
    {
      "source": "char_0",
      "target": "char_4",
      "relation": "suspects",
      "directed": true
    },
    {
      "source": "char_0",
      "target": "char_5",
      "relation": "suspects",
      "directed": true
    },
    {
      "source": "char_1",
      "target": "char_2",
      "relation": "suspects",
      "directed": true
    },
    {
      "source": "char_1",
      "target": "char_3",
      "relation": "suspects",
      "directed": true
    },
    {
      "source": "char_1",
      "target": "char_4",
      "relation": "suspects",
      "directed": true
    },
    {
      "source": "char_1",
      "target": "char_5",
      "relation": "suspects",
      "directed": true
    },
    {
      "source": "char_2",
      "target": "char_3",
      "relation": "deceives",
      "directed": true
    },
    {
      "source": "char_4",
      "target": "char_6",
      "relation": "deceives",
      "directed": true
    },
    {
      "source": "char_5",
      "target": "char_6",
      "relation": "deceives",
      "directed": true
    },
    {
      "source": "char_2",
      "target": "char_5",
      "relation": "protects",
      "directed": true
    },
    {
      "source": "char_3",
      "target": "char_2",
      "relation": "romantically involved with",
      "directed": true
    },
    {
      "source": "char_5",
      "target": "char_3",
      "relation": "romantically involved with",
      "directed": true
    },
    {
      "source": "char_4",
      "target": "char_2",
      "relation": "business partner of",
      "directed": true
    },
    {
      "source": "char_5",
      "target": "char_2",
      "relation": "business partner of",
      "directed": true
    },
    {
      "source": "char_6",
      "target": "loc_1",
      "relation": "near to",
      "directed": true
    },
    {
      "source": "char_0",
      "target": "char_5",
      "relation": "suspects",
      "directed": true
    },
    {
      "source": "char_1",
      "target": "char_5",
      "relation": "suspects",
      "directed": true
    },
    {
      "source": "char_2",
      "target": "char_5",
      "relation": "conflicts with",
      "directed": true
    },
    {
      "source": "char_3",
      "target": "char_5",
      "relation": "accuses",
      "directed": true
    },
    {
      "source": "char_4",
      "target": "char_5",
      "relation": "hires",
      "directed": true
    },
    {
      "source": "char_5",
      "target": "char_2",
      "relation": "works with",
      "directed": true
    },
    {
      "source": "char_6",
      "target": "char_3",
      "relation": "works with",
      "directed": true
    },
    {
      "source": "loc_1",
      "target": "loc_5",
      "relation": "near to",
      "directed": false
    },
    {
      "source": "org_0",
      "target": "loc_1",
      "relation": "located at",
      "directed": true
    },
    {
      "source": "char_0",
      "target": "char_2",
      "relation": "accuses",
      "directed": true
    },
    {
      "source": "char_0",
      "target": "char_3",
      "relation": "accuses",
      "directed": true
    },
    {
      "source": "char_0",
      "target": "char_4",
      "relation": "accuses",
      "directed": true
    },
    {
      "source": "char_0",
      "target": "char_5",
      "relation": "accuses",
      "directed": true
    },
    {
      "source": "char_1",
      "target": "char_2",
      "relation": "accuses",
      "directed": true
    },
    {
      "source": "char_1",
      "target": "char_3",
      "relation": "accuses",
      "directed": true
    },
    {
      "source": "char_1",
      "target": "char_4",
      "relation": "accuses",
      "directed": true
    },
    {
      "source": "char_1",
      "target": "char_5",
      "relation": "accuses",
      "directed": true
    },
    {
      "source": "char_2",
      "target": "char_3",
      "relation": "investigates",
      "directed": true
    },
    {
      "source": "char_4",
      "target": "char_6",
      "relation": "investigates",
      "directed": true
    },
    {
      "source": "char_5",
      "target": "char_6",
      "relation": "investigates",
      "directed": true
    },
    {
      "source": "char_2",
      "target": "char_5",
      "relation": "deceives",
      "directed": true
    },
    {
      "source": "char_3",
      "target": "char_2",
      "relation": "works with",
      "directed": true
    },
    {
      "source": "char_5",
      "target": "char_3",
      "relation": "works with",
      "directed": true
    },
    {
      "source": "char_6",
      "target": "loc_2",
      "relation": "near to",
      "directed": true
    },
    {
      "source": "char_0",
      "target": "char_1",
      "relation": "discovers",
      "directed": true
    },
    {
      "source": "char_2",
      "target": "char_3",
      "relation": "deceives",
      "directed": true
    },
    {
      "source": "char_4",
      "target": "char_6",
      "relation": "deceives",
      "directed": true
    },
    {
      "source": "char_5",
      "target": "char_6",
      "relation": "deceives",
      "directed": true
    },
    {
      "source": "char_2",
      "target": "char_5",
      "relation": "protects",
      "directed": true
    },
    {
      "source": "char_3",
      "target": "char_2",
      "relation": "romantically involved with",
      "directed": true
    },
    {
      "source": "char_5",
      "target": "char_3",
      "relation": "romantically involved with",
      "directed": true
    },
    {
      "source": "char_4",
      "target": "char_2",
      "relation": "business partner of",
      "directed": true
    },
    {
      "source": "char_5",
      "target": "char_2",
      "relation": "business partner of",
      "directed": true
    },
    {
      "source": "char_6",
      "target": "loc_1",
      "relation": "near to",
      "directed": true
    },
    {
      "source": "char_0",
      "target": "char_5",
      "relation": "suspects",
      "directed": true
    },
    {
      "source": "char_1",
      "target": "char_5",
      "relation": "suspects",
      "directed": true
    },
    {
      "source": "char_2",
      "target": "char_5",
      "relation": "conflicts with",
      "directed": true
    },
    {
      "source": "char_3",
      "target": "char_5",
      "relation": "accuses",
      "directed": true
    },
    {
      "source": "char_4",
      "target": "char_5",
      "relation": "hires",
      "directed": true
    },
    {
      "source": "char_5",
      "target": "char_2",
      "relation": "works with",
      "directed": true
    },
    {
      "source": "char_6",
      "target": "char_3",
      "relation": "works with",
      "directed": true
    }
  ],
  "metadata": {
    "entry_id": "NOV_208",
    "title": "The Secret History",
    "author": "Donna Tartt",
    "year": 1992,
    "medium": "Novel"
  }
}