{
  "characters": [
    {
      "id": "char_0",
      "name": "Philip Marlowe",
      "label": "Uninvolved",
      "features": {
        "gender": 0,
        "social_status": 0.7,
        "narrative_introduction_timing": 0.0,
        "has_alibi": 1,
        "present_at_crime_scene": -1,
        "has_motive": -1,
        "is_concealing_information": 1,
        "has_hidden_relationship": -1,
        "motive_type": -1,
        "narrative_prominence": 1
      }
    },
    {
      "id": "char_1",
      "name": "Moose Malloy",
      "label": "Villain",
      "features": {
        "gender": 0,
        "social_status": 0.2,
        "narrative_introduction_timing": 0.1,
        "has_alibi": -1,
        "present_at_crime_scene": 1,
        "has_motive": 1,
        "is_concealing_information": -1,
        "has_hidden_relationship": -1,
        "motive_type": "jealousy",
        "narrative_prominence": 0.5
      }
    },
    {
      "id": "char_2",
      "name": "Velma Valento / Mrs. Lewin Lockridge Grayle",
      "label": "Villain",
      "features": {
        "gender": 1,
        "social_status": 0.8,
        "narrative_introduction_timing": 0.3,
        "has_alibi": -1,
        "present_at_crime_scene": 1,
        "has_motive": 1,
        "is_concealing_information": 1,
        "has_hidden_relationship": 1,
        "motive_type": "money",
        "narrative_prominence": 0.8
      }
    },
    {
      "id": "char_3",
      "name": "Lt. Nulty",
      "label": "Uninvolved",
      "features": {
        "gender": 0,
        "social_status": 0.6,
        "narrative_introduction_timing": 0.2,
        "has_alibi": -1,
        "present_at_crime_scene": -1,
        "has_motive": -1,
        "is_concealing_information": -1,
        "has_hidden_relationship": -1,
        "motive_type": -1,
        "narrative_prominence": 0.2
      }
    },
    {
      "id": "char_4",
      "name": "Mrs. Jessie Florian",
      "label": "Witness",
      "features": {
        "gender": 1,
        "social_status": 0.3,
        "narrative_introduction_timing": 0.4,
        "has_alibi": 1,
        "present_at_crime_scene": -1,
        "has_motive": -1,
        "is_concealing_information": 1,
        "has_hidden_relationship": -1,
        "motive_type": -1,
        "narrative_prominence": 0.3
      }
    },
    {
      "id": "char_5",
      "name": "Lindsay Marriott",
      "label": "Victim",
      "features": {
        "gender": 0,
        "social_status": 0.6,
        "narrative_introduction_timing": 0.5,
        "has_alibi": -1,
        "present_at_crime_scene": 1,
        "has_motive": -1,
        "is_concealing_information": -1,
        "has_hidden_relationship": -1,
        "motive_type": -1,
        "narrative_prominence": 0.2
      }
    },
    {
      "id": "char_6",
      "name": "Anne Riordan",
      "label": "Witness",
      "features": {
        "gender": 1,
        "social_status": 0.5,
        "narrative_introduction_timing": 0.6,
        "has_alibi": 1,
        "present_at_crime_scene": -1,
        "has_motive": -1,
        "is_concealing_information": -1,
        "has_hidden_relationship": -1,
        "motive_type": -1,
        "narrative_prominence": 0.4
      }
    },
    {
      "id": "char_7",
      "name": "Lt. Randall",
      "label": "Uninvolved",
      "features": {
        "gender": 0,
        "social_status": 0.6,
        "narrative_introduction_timing": 0.7,
        "has_alibi": -1,
        "present_at_crime_scene": -1,
        "has_motive": -1,
        "is_concealing_information": -1,
        "has_hidden_relationship": -1,
        "motive_type": -1,
        "narrative_prominence": 0.3
      }
    },
    {
      "id": "char_8",
      "name": "Jules Amthor",
      "label": "Villain",
      "features": {
        "gender": 0,
        "social_status": 0.7,
        "narrative_introduction_timing": 0.8,
        "has_alibi": -1,
        "present_at_crime_scene": -1,
        "has_motive": -1,
        "is_concealing_information": 1,
        "has_hidden_relationship": -1,
        "motive_type": "money",
        "narrative_prominence": 0.2
      }
    },
    {
      "id": "char_9",
      "name": "Dr. Sonderborg",
      "label": "Villain",
      "features": {
        "gender": 0,
        "social_status": 0.7,
        "narrative_introduction_timing": 0.9,
        "has_alibi": -1,
        "present_at_crime_scene": -1,
        "has_motive": -1,
        "is_concealing_information": 1,
        "has_hidden_relationship": -1,
        "motive_type": "money",
        "narrative_prominence": 0.1
      }
    },
    {
      "id": "char_10",
      "name": "Red Norgaard",
      "label": "Uninvolved",
      "features": {
        "gender": 0,
        "social_status": 0.5,
        "narrative_introduction_timing": 1.0,
        "has_alibi": 1,
        "present_at_crime_scene": -1,
        "has_motive": -1,
        "is_concealing_information": -1,
        "has_hidden_relationship": -1,
        "motive_type": -1,
        "narrative_prominence": 0.1
      }
    },
    {
      "id": "char_11",
      "name": "John Wax",
      "label": "Villain",
      "features": {
        "gender": 0,
        "social_status": 0.9,
        "narrative_introduction_timing": 1.1,
        "has_alibi": -1,
        "present_at_crime_scene": -1,
        "has_motive": -1,
        "is_concealing_information": 1,
        "has_hidden_relationship": -1,
        "motive_type": "power",
        "narrative_prominence": 0.1
      }
    },
    {
      "id": "char_12",
      "name": "Laird Brunette",
      "label": "Villain",
      "features": {
        "gender": 0,
        "social_status": 0.8,
        "narrative_introduction_timing": 1.2,
        "has_alibi": -1,
        "present_at_crime_scene": -1,
        "has_motive": -1,
        "is_concealing_information": 1,
        "has_hidden_relationship": -1,
        "motive_type": "power",
        "narrative_prominence": 0.1
      }
    }
  ],
  "occupations": [
    {
      "id": "occ_0",
      "name": "Private detective",
      "features": {
        "authority_level": 0.4,
        "access_level": 0.6,
        "capability_level": 0.8
      }
    },
    {
      "id": "occ_1",
      "name": "Felon",
      "features": {
        "authority_level": 0.2,
        "access_level": 0.4,
        "capability_level": 0.5
      }
    },
    {
      "id": "occ_2",
      "name": "Nightclub owner",
      "features": {
        "authority_level": 0.6,
        "access_level": 0.7,
        "capability_level": 0.8
      }
    },
    {
      "id": "occ_3",
      "name": "Police detective",
      "features": {
        "authority_level": 0.9,
        "access_level": 0.7,
        "capability_level": 0.8
      }
    },
    {
      "id": "occ_4",
      "name": "Psychic",
      "features": {
        "authority_level": 0.3,
        "access_level": 0.5,
        "capability_level": 0.6
      }
    },
    {
      "id": "occ_5",
      "name": "Drug dealer",
      "features": {
        "authority_level": 0.2,
        "access_level": 0.4,
        "capability_level": 0.7
      }
    },
    {
      "id": "occ_6",
      "name": "Police chief",
      "features": {
        "authority_level": 1.0,
        "access_level": 0.8,
        "capability_level": 0.9
      }
    },
    {
      "id": "occ_7",
      "name": "Gambling boat operator",
      "features": {
        "authority_level": 0.6,
        "access_level": 0.5,
        "capability_level": 0.8
      }
    },
    {
      "id": "occ_8",
      "name": "Detective",
      "features": {
        "authority_level": 0.7,
        "access_level": 0.6,
        "capability_level": 0.8
      }
    }
  ],
  "locations": [
    {
      "id": "loc_0",
      "name": "Bay City (Santa Monica)",
      "features": {
        "accessibility": 0.7,
        "isolability": 0.3,
        "evidentiary_value": 0.5
      }
    },
    {
      "id": "loc_1",
      "name": "Florian's nightclub",
      "features": {
        "accessibility": 0.4,
        "isolability": 0.6,
        "evidentiary_value": 0.7
      }
    },
    {
      "id": "loc_2",
      "name": "Deserted canyon",
      "features": {
        "accessibility": 0.3,
        "isolability": 0.8,
        "evidentiary_value": 0.6
      }
    },
    {
      "id": "loc_3",
      "name": "Anne Riordan's house",
      "features": {
        "accessibility": 0.5,
        "isolability": 0.4,
        "evidentiary_value": 0.7
      }
    },
    {
      "id": "loc_4",
      "name": "Marlowe's office",
      "features": {
        "accessibility": 0.6,
        "isolability": 0.5,
        "evidentiary_value": 0.7
      }
    },
    {
      "id": "loc_5",
      "name": "Local hoodlum's club",
      "features": {
        "accessibility": 0.4,
        "isolability": 0.6,
        "evidentiary_value": 0.7
      }
    },
    {
      "id": "loc_6",
      "name": "Dr. Sonderborg's private hospital",
      "features": {
        "accessibility": 0.3,
        "isolability": 0.8,
        "evidentiary_value": 0.5
      }
    },
    {
      "id": "loc_7",
      "name": "Gambling boat",
      "features": {
        "accessibility": 0.3,
        "isolability": 0.8,
        "evidentiary_value": 0.6
      }
    }
  ],
  "organizations": [
    {
      "id": "org_0",
      "name": "Bay City police",
      "features": {
        "institutional_power": 0.9,
        "secrecy_level": 0.5,
        "financial_scale": 0.4
      }
    },
    {
      "id": "org_1",
      "name": "Local criminal network",
      "features": {
        "institutional_power": 0.6,
        "secrecy_level": 0.8,
        "financial_scale": 0.5
      }
    },
    {
      "id": "org_2",
      "name": "Radio station",
      "features": {
        "institutional_power": 0.4,
        "secrecy_level": 0.3,
        "financial_scale": 0.5
      }
    }
  ],
  "edges": [
    {
      "source": "char_0",
      "target": "occ_0",
      "relation": "employed as"
    },
    {
      "source": "char_4",
      "target": "loc_1",
      "relation": "resides at"
    },
    {
      "source": "char_1",
      "target": "char_2",
      "relation": "romantically involved with"
    },
    {
      "source": "char_0",
      "target": "char_1",
      "relation": "investigates"
    },
    {
      "source": "char_0",
      "target": "char_4",
      "relation": "interacts with"
    },
    {
      "source": "char_1",
      "target": "loc_1",
      "relation": "present at"
    },
    {
      "source": "char_1",
      "target": "char_2",
      "relation": "searches for"
    },
    {
      "source": "char_5",
      "target": "occ_0",
      "relation": "hires"
    },
    {
      "source": "char_5",
      "target": "char_0",
      "relation": "interacts with"
    },
    {
      "source": "char_5",
      "target": "loc_3",
      "relation": "present at"
    },
    {
      "source": "char_6",
      "target": "char_0",
      "relation": "finds"
    },
    {
      "source": "char_6",
      "target": "char_5",
      "relation": "discovers body of"
    },
    {
      "source": "char_7",
      "target": "occ_3",
      "relation": "employed by"
    },
    {
      "source": "char_0",
      "target": "char_8",
      "relation": "present at"
    },
    {
      "source": "char_0",
      "target": "loc_6",
      "relation": "escapes from"
    },
    {
      "source": "char_1",
      "target": "char_0",
      "relation": "works with"
    },
    {
      "source": "char_1",
      "target": "loc_4",
      "relation": "hides in"
    },
    {
      "source": "char_2",
      "target": "char_0",
      "relation": "confronts"
    },
    {
      "source": "char_2",
      "target": "char_5",
      "relation": "kills"
    },
    {
      "source": "char_2",
      "target": "char_1",
      "relation": "informs on"
    },
    {
      "source": "char_9",
      "target": "loc_6",
      "relation": "operates"
    },
    {
      "source": "char_0",
      "target": "char_8",
      "relation": "accuses"
    },
    {
      "source": "char_11",
      "target": "org_0",
      "relation": "leads"
    },
    {
      "source": "char_10",
      "target": "org_0",
      "relation": "fired by"
    },
    {
      "source": "char_12",
      "target": "loc_5",
      "relation": "operates"
    },
    {
      "source": "char_12",
      "target": "org_1",
      "relation": "controls"
    },
    {
      "source": "char_0",
      "target": "char_12",
      "relation": "sneaks on board with"
    },
    {
      "source": "char_0",
      "target": "char_2",
      "relation": "hired by"
    },
    {
      "source": "char_2",
      "target": "char_5",
      "relation": "uses to keep in line"
    },
    {
      "source": "char_2",
      "target": "char_1",
      "relation": "convinced to set up"
    },
    {
      "source": "char_0",
      "target": "char_6",
      "relation": "romantically involved with"
    }
  ],
  "metadata": {
    "entry_id": "NOV_084",
    "title": "Farewell, My Lovely",
    "author": "Raymond Chandler",
    "year": 1940,
    "medium": "Novel"
  }
}