{
  "characters": [
    {
      "id": "char_0",
      "name": "Detective Inspector Robert Lewis",
      "label": "Uninvolved",
      "features": {
        "gender": 0,
        "social_status": 0.75,
        "narrative_introduction_timing": 0.0,
        "has_alibi": -1,
        "present_at_crime_scene": -1,
        "has_motive": 0,
        "is_concealing_information": -1,
        "has_hidden_relationship": -1,
        "motive_type": -1,
        "narrative_prominence": 1.0
      }
    },
    {
      "id": "char_1",
      "name": "Sergeant James Hathaway",
      "label": "Uninvolved",
      "features": {
        "gender": 0,
        "social_status": 0.75,
        "narrative_introduction_timing": 0.25,
        "has_alibi": -1,
        "present_at_crime_scene": -1,
        "has_motive": 0,
        "is_concealing_information": -1,
        "has_hidden_relationship": -1,
        "motive_type": -1,
        "narrative_prominence": 0.75
      }
    },
    {
      "id": "char_2",
      "name": "Director or Principal of the music school",
      "label": "Uninvolved",
      "features": {
        "gender": -1,
        "social_status": 0.95,
        "narrative_introduction_timing": 0.5,
        "has_alibi": -1,
        "present_at_crime_scene": -1,
        "has_motive": -1,
        "is_concealing_information": -1,
        "has_hidden_relationship": -1,
        "motive_type": -1,
        "narrative_prominence": 0.5
      }
    },
    {
      "id": "char_3",
      "name": "Senior teaching staff",
      "label": "Uninvolved",
      "features": {
        "gender": -1,
        "social_status": 0.85,
        "narrative_introduction_timing": 0.25,
        "has_alibi": -1,
        "present_at_crime_scene": -1,
        "has_motive": -1,
        "is_concealing_information": -1,
        "has_hidden_relationship": -1,
        "motive_type": -1,
        "narrative_prominence": 0.5
      }
    },
    {
      "id": "char_4",
      "name": "Other students",
      "label": "Uninvolved",
      "features": {
        "gender": -1,
        "social_status": 0.35,
        "narrative_introduction_timing": 0.25,
        "has_alibi": -1,
        "present_at_crime_scene": -1,
        "has_motive": -1,
        "is_concealing_information": -1,
        "has_hidden_relationship": -1,
        "motive_type": -1,
        "narrative_prominence": 0.5
      }
    },
    {
      "id": "char_5",
      "name": "Parents",
      "label": "Uninvolved",
      "features": {
        "gender": -1,
        "social_status": 0.7,
        "narrative_introduction_timing": 0.25,
        "has_alibi": -1,
        "present_at_crime_scene": -1,
        "has_motive": -1,
        "is_concealing_information": -1,
        "has_hidden_relationship": -1,
        "motive_type": -1,
        "narrative_prominence": 0.5
      }
    },
    {
      "id": "char_6",
      "name": "Victim",
      "label": "Victim",
      "features": {
        "gender": -1,
        "social_status": 0.35,
        "narrative_introduction_timing": 0.0,
        "has_alibi": -1,
        "present_at_crime_scene": -1,
        "has_motive": -1,
        "is_concealing_information": -1,
        "has_hidden_relationship": -1,
        "motive_type": -1,
        "narrative_prominence": 0.5
      }
    },
    {
      "id": "char_7",
      "name": "Killer",
      "label": "Villain",
      "features": {
        "gender": -1,
        "social_status": 0.85,
        "narrative_introduction_timing": 0.5,
        "has_alibi": 0,
        "present_at_crime_scene": 1,
        "has_motive": 1,
        "is_concealing_information": -1,
        "has_hidden_relationship": -1,
        "motive_type": -1,
        "narrative_prominence": 0.5
      }
    }
  ],
  "occupations": [
    {
      "id": "occ_0",
      "name": "Detective",
      "features": {
        "authority_level": 0.9,
        "access_level": 0.8,
        "capability_level": 0.9
      }
    },
    {
      "id": "occ_1",
      "name": "Sergeant",
      "features": {
        "authority_level": 0.75,
        "access_level": 0.8,
        "capability_level": 0.75
      }
    },
    {
      "id": "occ_2",
      "name": "Director or Principal of the music school",
      "features": {
        "authority_level": 1,
        "access_level": 0.9,
        "capability_level": 0.85
      }
    },
    {
      "id": "occ_3",
      "name": "Senior teaching staff",
      "features": {
        "authority_level": 0.75,
        "access_level": 0.6,
        "capability_level": 0.8
      }
    },
    {
      "id": "occ_4",
      "name": "Student",
      "features": {
        "authority_level": 0.25,
        "access_level": 0.6,
        "capability_level": 0.35
      }
    },
    {
      "id": "occ_5",
      "name": "Parent",
      "features": {
        "authority_level": 0.2,
        "access_level": 0.4,
        "capability_level": 0.3
      }
    }
  ],
  "locations": [
    {
      "id": "loc_0",
      "name": "Music school",
      "features": {
        "accessibility": 0.8,
        "isolability": 0.5,
        "evidentiary_value": 0.7
      }
    },
    {
      "id": "loc_1",
      "name": "Crime scene",
      "features": {
        "accessibility": 0.3,
        "isolability": 0.8,
        "evidentiary_value": 0.9
      }
    }
  ],
  "organizations": [
    {
      "id": "org_0",
      "name": "Music school",
      "features": {
        "institutional_power": 0.85,
        "secrecy_level": 0.6,
        "financial_scale": 0.7
      }
    }
  ],
  "edges": [
    {
      "source": "char_0",
      "target": "occ_0",
      "relation": "employed as",
      "directed": true
    },
    {
      "source": "char_1",
      "target": "occ_1",
      "relation": "employed as",
      "directed": true
    },
    {
      "source": "char_2",
      "target": "occ_2",
      "relation": "employed as",
      "directed": true
    },
    {
      "source": "char_3",
      "target": "occ_3",
      "relation": "employed as",
      "directed": true
    },
    {
      "source": "char_4",
      "target": "occ_4",
      "relation": "employed as",
      "directed": true
    },
    {
      "source": "char_5",
      "target": "occ_5",
      "relation": "employed as",
      "directed": true
    },
    {
      "source": "char_6",
      "target": "occ_4",
      "relation": "is a",
      "directed": true
    },
    {
      "source": "char_7",
      "target": "occ_0",
      "relation": "investigates",
      "directed": true
    },
    {
      "source": "char_7",
      "target": "char_6",
      "relation": "kills",
      "directed": true
    },
    {
      "source": "loc_0",
      "target": "org_0",
      "relation": "located at",
      "directed": false
    },
    {
      "source": "loc_1",
      "target": "loc_0",
      "relation": "near to",
      "directed": false
    }
  ],
  "metadata": {
    "entry_id": "TVE_068",
    "title": "Lewis: The Gift of Promise",
    "author": "Bill Anderson",
    "year": 2008,
    "medium": "TV Episode"
  }
}